LICENSE
README.md
setup.py
csv_join.egg-info/PKG-INFO
csv_join.egg-info/SOURCES.txt
csv_join.egg-info/dependency_links.txt
csv_join.egg-info/entry_points.txt
csv_join.egg-info/requires.txt
csv_join.egg-info/top_level.txt
csvjoin/__init__.py
csvjoin/__main__.py
csvjoin/csvjoin.py