Metadata-Version: 2.1
Name: csv-join
Version: 1.0.8
Summary: join csv files in SQL
Home-page: https://github.com/walkerever/csv-join
Author: Yonghang Wang
Author-email: wyhang@gmail.com
License: Apache 2
Keywords: csv,query,sql,console
Platform: UNKNOWN
Classifier: License :: OSI Approved :: Apache Software License
License-File: LICENSE
